celery_dill_serializer/__init__.py
celery_dill_serializer-0.1.3.dist-info/DESCRIPTION.rst
celery_dill_serializer-0.1.3.dist-info/METADATA
celery_dill_serializer-0.1.3.dist-info/RECORD
celery_dill_serializer-0.1.3.dist-info/WHEEL
celery_dill_serializer-0.1.3.dist-info/metadata.json
celery_dill_serializer-0.1.3.dist-info/top_level.txt
