Metadata-Version: 2.0
Name: celery-dill-serializer
Version: 0.1.3
Summary: Dill serializer for Celery 4.0+
Home-page: https://github.com/mathiasose/celery_dill_serializer
Author: Mathias Ose
Author-email: mathias.ose@gmail.com
License: UNKNOWN
Download-URL: https://github.com/mathiasose/celery_dill_serializer/releases/tag/0.1.3
Keywords: celery,dill,serialization
Platform: UNKNOWN
Classifier: Development Status :: 4 - Beta
Classifier: License :: OSI Approved :: MIT License
Requires-Dist: celery (>=4.0.2)
Requires-Dist: dill (>=0.2.5)
